{
    "UserAgent": "Direct type - CognitoAuth",
    "Version": "1.0.0",
    "IdentityManager": {
        "Default": {}
    },
    "CredentialsProvider": {
        "CognitoIdentity": {
            "Default": {
                "PoolId": "ap-northeast-1:c6e549ed-db63-4016-8386-55cad2c2f020",
                "Region": "ap-northeast-1"
            }
        }
    },
    "CognitoUserPool": {
        "Default": {
            "PoolId": "ap-northeast-1_xXjzdlVk7",
            "AppClientId": "2ia1qf6neseceuvb77inviq99c",
            "Region": "ap-northeast-1"
        }
    },
    "Auth": {
      "Default": {
        "authenticationFlowType": "CUSTOM_AUTH"
      }
    }
}
